schemaorg_lite-0.3.2.dist-info/METADATA
schemaorg_lite-0.3.2.dist-info/WHEEL
schemaorg_lite-0.3.2.dist-info/entry_points.txt
schemaorg_lite-0.3.2.dist-info/licenses/LICENSE
schemaorg_lite/__init__.py
schemaorg_lite/data/__init__.py
schemaorg_lite/data/ext/attic/attic.ttl
schemaorg_lite/data/ext/auto/auto.ttl
schemaorg_lite/data/ext/bib/bsdo-1.0.ttl
schemaorg_lite/data/ext/bib/bsdo-atlas-examples.txt
schemaorg_lite/data/ext/bib/bsdo-audiobook-examples.txt
schemaorg_lite/data/ext/bib/bsdo-chapter-examples.txt
schemaorg_lite/data/ext/bib/bsdo-collection-examples.txt
schemaorg_lite/data/ext/bib/bsdo-newspaper-examples.txt
schemaorg_lite/data/ext/bib/bsdo-thesis-examples.txt
schemaorg_lite/data/ext/bib/bsdo-translation-examples.txt
schemaorg_lite/data/ext/bib/comics-examples.txt
schemaorg_lite/data/ext/health-lifesci/MedicalScholarlyArticle-examples.txt
schemaorg_lite/data/ext/health-lifesci/drug-example.txt
schemaorg_lite/data/ext/health-lifesci/med-health-core.ttl
schemaorg_lite/data/ext/health-lifesci/medicalCondition-examples.txt
schemaorg_lite/data/ext/health-lifesci/medicalGuideline-examples.txt
schemaorg_lite/data/ext/health-lifesci/medicalWebpage-examples.txt
schemaorg_lite/data/ext/health-lifesci/physical-activity-and-exercise.ttl
schemaorg_lite/data/ext/meta/meta.jsonld.someday.txt
schemaorg_lite/data/ext/meta/meta.ttl
schemaorg_lite/data/ext/pending/issue-1045-examples.txt
schemaorg_lite/data/ext/pending/issue-1045.ttl
schemaorg_lite/data/ext/pending/issue-1050-examples.txt
schemaorg_lite/data/ext/pending/issue-1050.ttl
schemaorg_lite/data/ext/pending/issue-1062-examples.txt
schemaorg_lite/data/ext/pending/issue-1062.ttl
schemaorg_lite/data/ext/pending/issue-1083.ttl
schemaorg_lite/data/ext/pending/issue-1156-examples.txt
schemaorg_lite/data/ext/pending/issue-1156.ttl
schemaorg_lite/data/ext/pending/issue-1244.ttl
schemaorg_lite/data/ext/pending/issue-1253-examples.txt
schemaorg_lite/data/ext/pending/issue-1253.ttl
schemaorg_lite/data/ext/pending/issue-1375.ttl
schemaorg_lite/data/ext/pending/issue-1389-examples.txt
schemaorg_lite/data/ext/pending/issue-1397.ttl
schemaorg_lite/data/ext/pending/issue-1401.ttl
schemaorg_lite-0.3.2.dist-info/RECORD
