Metadata-Version: 2.1
Name: schemaorg-lite
Version: 0.3.2
Summary: Python functions for applied use of schema.org
Keywords: openschemas,schema.org
Author-Email: Vanessa Sochat <vsoch@users.noreply.github.com>, lesleslie <les@wedgwoodwebworks.com>
Maintainer-Email: lesleslie <les@wedgwoodwebworks.com>, Vanessa Sochat <vsoch@users.noreply.github.com>
License: BSD-3-Clause
Classifier: Intended Audience :: Developers
Classifier: Intended Audience :: Information Technology
Classifier: License :: OSI Approved :: GNU Affero General Public License v3 or later (AGPLv3+)
Classifier: Operating System :: Unix
Classifier: Programming Language :: Python
Classifier: Programming Language :: Python :: 3
Classifier: Topic :: Software Development
Project-URL: Homepage, https://github.com/lesleslie/schemaorg-lite
Project-URL: Documentation, https://github.com/lesleslie/schemaorg-lite
Project-URL: Repository, https://github.com/lesleslie/schemaorg-lite
Requires-Python: >=3.13
